MANIFEST.in
setup.py
PyHBase.egg-info/PKG-INFO
PyHBase.egg-info/SOURCES.txt
PyHBase.egg-info/dependency_links.txt
PyHBase.egg-info/requires.txt
PyHBase.egg-info/top_level.txt
examples/pyhbase-cli
pyhbase/__init__.py
pyhbase/connection.py
pyhbase/schema/hbase.avpr