Metadata-Version: 1.0
Name: PyHBase
Version: 0.1.0
Summary: High-level Python interface to HBase
Home-page: http://github.com/hammer/pyhbase/
Author: Jeff Hammerbacher
Author-email: hammer@cloudera.com
License: UNKNOWN
Keywords: database hbase avro
Platform: UNKNOWN
